mcp_zendesk/__init__.py
mcp_zendesk/server.py
mcp_zendesk-0.0.2.dist-info/METADATA
mcp_zendesk-0.0.2.dist-info/WHEEL
mcp_zendesk-0.0.2.dist-info/entry_points.txt
mcp_zendesk-0.0.2.dist-info/top_level.txt
mcp_zendesk-0.0.2.dist-info/RECORD
